yaigr/__init__.py
yaigr/yaigr.py
yaigr-1.0.0.dist-info/LICENSE
yaigr-1.0.0.dist-info/METADATA
yaigr-1.0.0.dist-info/WHEEL
yaigr-1.0.0.dist-info/top_level.txt
yaigr-1.0.0.dist-info/RECORD
