Metadata-Version: 2.1
Name: yaigr
Version: 1.0.0
Summary: Image generator
Author-email: Alexey Kosenko <box@alkosenko.tech>
Classifier: Programming Language :: Python :: 3
Classifier: License :: OSI Approved :: MIT License
Classifier: Operating System :: OS Independent
Requires-Python: >=3.9
License-File: LICENSE
